[
    {
        "created_time": "2017-07-22T04:39:07+0000",
        "from": {
            "name": "Patricia Parra",
            "id": "10207268121003456"
        },
        "message": "J.A.KAST Se distingue por su valentía y aplomo,es un hombre recto...nuestras oraciones por su vida y Campaña!!!Grande JAK!!!",
        "id": "1434243133334175_1434576043300884"
    },
    {
        "created_time": "2017-07-22T15:01:05+0000",
        "from": {
            "name": "Tamara Nataly Gutierrez Barrios",
            "id": "10213825703772452"
        },
        "message": "Atencion!!! \nNo por asistir a ciertar marchas o actividad te convierte en!?? \nO por decir que soy lavadora me trasformare en eso ? No\n\nEl unico candidato presidencial que va por valores y no por con veniencia o palestra es Abraham larrondo ,principios de vida! \nPartido unico en chile desde cristianos a la ciudad!\nSumate queda poco!!!\n#yosoy pacc \nY tu",
        "id": "1434243133334175_1435153653243123"
    },
    {
        "created_time": "2017-07-21T21:28:17+0000",
        "from": {
            "name": "Hector Acuña",
            "id": "575491175977148"
        },
        "message": "Ciudadanos de Chile elijamos a autoridades que amen la familia, el bien de nuestra sociedad, los valores. ya no saquemos insensatos y corruptos.....que Dios bendia a Chile.",
        "id": "1434243133334175_1434254603333028"
    },
    {
        "created_time": "2017-07-21T22:53:57+0000",
        "from": {
            "name": "Rodrigo Verdugo Salazar",
            "id": "555146324629382"
        },
        "message": "Esta es el tipo de autoridades k necesita nuestra nacion ...hombre de conviccion y no de emocion..hombres de valor...valientes k valoran. Y aman la vida... K consideran a Dios. Y respetan y valoran su creacion....!!!!!siga firme alguien k se ponga la camiseta por los inocentes.....espero k siga asi ...tiene mi apoyo!!!!bien ....mis respetos a su persona......",
        "id": "1434243133334175_1434328303325658"
    },
    {
        "created_time": "2017-07-22T10:46:36+0000",
        "from": {
            "name": "Gonzalo Leonel Atenas Palacios",
            "id": "678727388884415"
        },
        "message": "Simplemente decir que \"los homosexuales\" votarán por mi por ser \"una persona correcta\", dios mío, cuanto AMARILLISMO.-",
        "id": "1434243133334175_1434893616602460"
    },
    {
        "created_time": "2017-07-25T04:42:12+0000",
        "from": {
            "name": "Mariela R Varela",
            "id": "10207209136443747"
        },
        "message": "Sr. Kast definitivamente me   está convenciendo ... yo y mi familia votaremos por quien sea consecuente y represente nuedtros valores cristianos y ud se acerca bastante.... no veo imposible su llegada a la presidencia... todo puede pasar.... aunque muchos quieran ocultarlo y negarlo, somos millones los que defendemos la familia asi que facilmente podría llegar a la moneda. \nsaludos!",
        "id": "1434243133334175_1438904689534686"
    },
    {
        "created_time": "2017-07-21T22:23:56+0000",
        "from": {
            "name": "Ana Verónica",
            "id": "887840081227620"
        },
        "message": "Que bien que la gente se de cuenta de las leyes que se están votando en el congreso para homosexualizar a los niños,muchos no creen,pero como dijo Agustín Laje todavía estamos a tiempo de saltar de la olla antes que nos cocinen.",
        "id": "1434243133334175_1434306206661201"
    },
    {
        "created_time": "2017-07-24T19:12:24+0000",
        "from": {
            "name": "Michael Angelo Canario Monsalve",
            "id": "10154699634782050"
        },
        "message": "Yo voto kast y mi familia también \ninvito a todos los padres cristiano a ser consecuente con su voto al igual que lo que profesamos recuerden \nDios ve hasta en las votaciones no regalaré mi primogenitura por un plato de lentejas votaré por alguien que si me representa de verdad como ciudadano y como cristiano y que este dispuesto a defender mis ideales y los de mi generación \nDios le bendiga junto a su familia \nCiudad de Lota y Coronel esta con usted",
        "id": "1434243133334175_1438471166244705"
    },
    {
        "created_time": "2017-07-22T01:05:22+0000",
        "from": {
            "name": "Claudio Matamala Aguila",
            "id": "1470664062950746"
        },
        "message": "MUY BIEN , EXCELENTE  nunca e votado por que no le e creido a nadie  pero...e seguido a este candidato y es valiente , coherente, sensato  NO SE AVERGÜENCE DEL VANGELIO POR QUE ES PODER DE DIOS.  DIOS LE BENDIGA",
        "id": "1434243133334175_1434413979983757"
    },
    {
        "created_time": "2017-07-22T07:45:19+0000",
        "from": {
            "name": "Cecilia Verónica Gómez Williams",
            "id": "788465554546739"
        },
        "message": "Gracias y felicitaciones José Antonio Kast, la familia es la causa más noble y los valores están representados en el bus de la esperanza.",
        "id": "1434243133334175_1434759716615850"
    },
    {
        "created_time": "2017-07-21T21:27:42+0000",
        "from": {
            "name": "Loida Alvarado Morales",
            "id": "10210450546363773"
        },
        "message": "Que todo el pueblo cristiano y la ciudadanía que defiende la familia este es el candidato...José Antonio kast vamos con todo!!!",
        "id": "1434243133334175_1434254309999724"
    },
    {
        "created_time": "2017-07-21T21:37:46+0000",
        "from": {
            "name": "Riccardo Rich",
            "id": "10204361963313671"
        },
        "message": "Creo que UD como persona con cultura y educación, como actor importante de la política debería asumir una actitud más conciliadora y de entendimiento. Todos debemos respetarnos. Por supuesto que hay que proteger a los niños. Pero es un error hacer ver a un sector social como peligroso cuando cada caso se debe analizar de manera particular puesto que es en el sector heterosexual donde se dan la mayoría de abusos.",
        "id": "1434243133334175_1434260253332463"
    },
    {
        "created_time": "2017-07-21T21:16:28+0000",
        "from": {
            "name": "Rosa Cecilia Zapata Lopez",
            "id": "10203486516111239"
        },
        "message": "Cuando la Ley sea una terminarán las desigualdades. La Ley se enseña el Juicio del hombre está escrito. La biblia es la Ley del amor, la verdad y la Justicia. La Ley perfecta es una para todos y todos para uno. Las leyes sin el juicio de Dios son prejuicios de nunca acabar.",
        "id": "1434243133334175_1434246080000547"
    },
    {
        "created_time": "2017-07-22T05:57:56+0000",
        "from": {
            "name": "Claudia Martínez",
            "id": "259038717904414"
        },
        "message": "Éste 67% es el porcentaje de ciudadanos que votará por José Antonio Kast para presidente en las próximas elecciones. https://t.co/Ijk9ybif5Y",
        "id": "1434243133334175_1434651653293323"
    },
    {
        "created_time": "2017-07-23T14:58:31+0000",
        "from": {
            "name": "Yosef Valenzuela",
            "id": "980561888652863"
        },
        "message": "No voy a votar por un católica. Ultra , que no critica la dictadura pasada , no cree en el divorcio , que es bíblico , dice que el tema de la araucania se arregla con milicos en la calle , un catolico que dice que los que tienen que ser educados los mejores .... son católicos que. No creen en los evangélicos , gente que cree que ellos fueron llamados por dios para gobernar , que no creen separación del estado , donde los evangélicos eran botados al mar y enterrados en el cerro Santa Lucía ... son sepulcros emblanquecidos ...",
        "id": "1434243133334175_1436886566403165"
    },
    {
        "created_time": "2017-07-22T00:18:16+0000",
        "from": {
            "name": "Mario Fortuna",
            "id": "125499088029090"
        },
        "message": "Muy bien habitantes puerto montt por algo bueno hay que dar el ejemplo y tener tolerancia hay otro que la exijen pero no la tienen.",
        "id": "1434243133334175_1434380896653732"
    },
    {
        "created_time": "2017-07-21T21:29:16+0000",
        "from": {
            "name": "Riccardo Rich",
            "id": "10204361963313671"
        },
        "message": "Defiendalos de la pobreza, de la miseria, del bullying, de la discriminación, de los violadores, de la ignorancia. Es vergonzoso que tergiversen todo, y que desvíen los fondos de ciertas cuestiones, lamentable. Las personas todas tenemos los mismos derechos por naturaleza y debemos convivir en paz. Lamento profundamente que una persona como UD no contribuya al entendimiento. Tristeza.",
        "id": "1434243133334175_1434255233332965"
    },
    {
        "created_time": "2017-07-21T21:43:55+0000",
        "from": {
            "name": "Riccardo Rich",
            "id": "10204361963313671"
        },
        "message": "Las leyes de adopción deben ser estrictas siempre y para todos. La educación no es adoctrinamiento, ni una forma de convencer a nadie sobre sus gustos personales.",
        "id": "1434243133334175_1434265196665302"
    },
    {
        "created_time": "2017-07-22T00:09:20+0000",
        "from": {
            "name": "Daniel Mick Mejías",
            "id": "1940430496276849"
        },
        "message": "No tengo la menor duda, que mientras más pase el tiempo si antes de las elecciones, Los Argumentos serán los encargados de orientar a la gente correcta, aburrida de engaños a volver a creer en una posibilidad cierta de un cambio de verdad...que es claramente el objetivo de nuestro candidato Sr José Antonio Kast...",
        "id": "1434243133334175_1434374859987669"
    },
    {
        "created_time": "2017-07-21T22:09:12+0000",
        "from": {
            "name": "Javier Cornejo Albornoz",
            "id": "224585038065691"
        },
        "message": "acaba de aparecer el hombre que reprentara a chile.un hombre con agallas y coherencia a la hora de exponer una tematica delante de la evidente intolerancia",
        "id": "1434243133334175_1434291106662711"
    },
    {
        "created_time": "2017-07-21T21:20:20+0000",
        "from": {
            "name": "Claudia Martínez",
            "id": "259038717904414"
        },
        "message": "Necesitamos un gobierno con enfoque de familia, no de género. Legislar con bases científicas, no ideológicas.",
        "id": "1434243133334175_1434249576666864"
    },
    {
        "created_time": "2017-07-23T19:11:45+0000",
        "from": {
            "name": "Enrique Sandoval Arcos",
            "id": "1187945807900332"
        },
        "message": "si sale yo y mi familia votaremos por ested el Señor lo bendiga",
        "id": "1434243133334175_1437169143041574"
    },
    {
        "created_time": "2017-07-22T01:58:13+0000",
        "from": {
            "name": "Javier Oyarzún",
            "id": "1888657204683160"
        },
        "message": "Bendiciones puerto Montt a su gente hermosa y bien por José Antonio kast, ojala sea nuestro futuro presidente.",
        "id": "1434243133334175_1434457296646092"
    },
    {
        "created_time": "2017-07-21T21:52:16+0000",
        "from": {
            "name": "Katty De Pinto",
            "id": "475138359304092"
        },
        "message": "EL HOMBRE QUE PONGA POR DELANTE A DIOS, ESE SERA BENDECIDO...",
        "id": "1434243133334175_1434273526664469"
    },
    {
        "created_time": "2017-07-22T14:41:27+0000",
        "from": {
            "name": "Felipe Donoso",
            "id": "159356201295561"
        },
        "message": "Es cierto , mucho homosexual decente votará por usted , ya que he hablado con muchos de ellos , dicen no ser representados por el lgbt  ni menos por el vocero , viven sus vidas tranquilos , no molestan a nadie y a esa hora trabajan, no andan tirando piedras , mis respetos por los homosexuales decentes de este país .",
        "id": "1434243133334175_1435133193245169"
    },
    {
        "created_time": "2017-07-22T03:17:02+0000",
        "from": {
            "name": "Marilyn Piña",
            "id": "10210521064288233"
        },
        "message": "Gracias a todos los presente, ,, y a nuestro futuro presidente.. José Antonio Kast",
        "id": "1434243133334175_1434521866639635"
    },
    {
        "created_time": "2017-07-21T22:33:32+0000",
        "from": {
            "name": "Nicolas Alonso Mendoza Mahncke",
            "id": "10152363156165631"
        },
        "message": "¿Y de cuando que se dio vuelta la chaqueta con este asunto?",
        "id": "1434243133334175_1434311879993967"
    },
    {
        "created_time": "2017-07-21T21:46:55+0000",
        "from": {
            "name": "Edwin Duarte Olivares",
            "id": "392530740925110"
        },
        "message": "Señor kast no estoy ni ahí con Ud por favor no mande propaganda  a mi Facebook",
        "id": "1434243133334175_1434267456665076"
    },
    {
        "created_time": "2017-07-22T01:15:10+0000",
        "from": {
            "name": "Octavio Hg",
            "id": "308409205981617"
        },
        "message": "VAMOS SR; JAK ,  ud sera el próximo presidente de chile ,, y chile lo necesita...",
        "id": "1434243133334175_1434419739983181"
    },
    {
        "created_time": "2017-07-22T05:45:43+0000",
        "from": {
            "name": "Cristian Garcia Hormazabal",
            "id": "10153508632777436"
        },
        "message": "José Antonio Kast. Usted dedíquese a encontrar el punto exacto que puede movilizar a una ciudadanía apática y dormida. Sea la voz honesta y comprometida de ese gran sector y... Será nuestro presidente.\nSea serio, reflexivo antes de hablar montado en la efímera emoción, no juegue con las esperanzas de la gente agotada, huya del populismo, busque el bien de su país y en estos momentos PRIVILEGIE A LAS FAMILIAS. Y, le irá bien.\nEnfóquese en la mayoría conservadora pues allí está la rabia y el descontento. Díganos, prométanos y cumpla que no se meterá con nuestros hijos y asegurese que nuestros hijos serán educados por nosotros y listo. Usted es y será el candidato de mi familia, y le aseguro que de miles más.\nÁnimo, las condiciones están de su lado. USE SU OPORTUNIDAD, PERO NO ABUSE DE ELLA. Hágalo bien José, hágalo como debe ser.\n\nDaniel Esteban Vasquez Cofre",
        "id": "1434243133334175_1434640579961097"
    },
    {
        "created_time": "2017-07-21T21:24:50+0000",
        "from": {
            "name": "Claudia Martínez",
            "id": "259038717904414"
        },
        "message": "Que caiga la ideocracia de Bachelet!!!! Kast para presidente!!!",
        "id": "1434243133334175_1434252536666568"
    },
    {
        "created_time": "2017-07-21T22:20:19+0000",
        "from": {
            "name": "Ricci Martin Voyager",
            "id": "528608750618476"
        },
        "message": "Bien bien gente.   Eso si esta muy bueno.  Salir a las calles a demostrar el descontento de todos los chilenos.",
        "id": "1434243133334175_1434304033328085"
    },
    {
        "created_time": "2017-07-21T21:16:11+0000",
        "from": {
            "name": "Marcelo Cabral",
            "id": "730905840348302"
        },
        "message": "La gorda corrupta comunista  del Frente Terrorista Manuel Rodriguez quiere pervertir el país. No lo permita.",
        "id": "1434243133334175_1434245630000592"
    },
    {
        "created_time": "2017-07-21T21:25:44+0000",
        "from": {
            "name": "Graciela Lincoñir",
            "id": "511055702593489"
        },
        "message": "Q bueno, esto es lo que necesitamos en chile la defensa de la familia y no la ideología de género.",
        "id": "1434243133334175_1434253066666515"
    },
    {
        "created_time": "2017-07-22T19:07:21+0000",
        "from": {
            "name": "Adolfo Cortes",
            "id": "10203697810828220"
        },
        "message": "Bravo JAK, cada día mas gente se suma, solo debes hacer bien tu política, la familia y los ciudadanos de trabajo están primero",
        "id": "1434243133334175_1435506163207872"
    },
    {
        "created_time": "2017-07-22T00:36:14+0000",
        "from": {
            "name": "José Navarrete Viveros",
            "id": "168279453511927"
        },
        "message": "Mientras se mantenga firme en sus pricipios y valores y no se averguenze del evangelio, Dios le ayudara.",
        "id": "1434243133334175_1434395523318936"
    },
    {
        "created_time": "2017-07-23T00:06:02+0000",
        "from": {
            "name": "Maritza Serrano",
            "id": "243863136078295"
        },
        "message": "Vamos mi presidente , no le había podido hacer barra ya que denunciaron mi cuenta y estaba suspendida..   Vamos , la gente se esta dando cuenta que usted no es turbio como los otros candidatos  y eso se valora!!!",
        "id": "1434243133334175_1435918056500016"
    },
    {
        "created_time": "2017-07-24T17:53:17+0000",
        "from": {
            "name": "Nelda Elizabeth Vasquez Ulloa",
            "id": "10210744392234605"
        },
        "message": "Que bueno, yo apoyó el bus que bueno que llego a Puerto Montt yo también voto por usted.",
        "id": "1434243133334175_1438395189585636"
    },
    {
        "created_time": "2017-07-21T22:03:01+0000",
        "from": {
            "name": "Pablo Cisternas",
            "id": "1192970504108952"
        },
        "message": "El futuro presidente vamos que se puede,con la verdad por delante",
        "id": "1434243133334175_1434285949996560"
    },
    {
        "created_time": "2017-07-22T00:58:00+0000",
        "from": {
            "name": "Raul Vergara Bustamante",
            "id": "10213382478339191"
        },
        "message": "Tenemos que salir las calles a demostrar que la familia esta primero,  hombre, mujer , hijos igual familia.",
        "id": "1434243133334175_1434407049984450"
    },
    {
        "created_time": "2017-07-21T23:37:28+0000",
        "from": {
            "name": "Marcelo Cofre",
            "id": "206342483085925"
        },
        "message": "Vamos jose Antonio mi voto es para ti ya que piñera es un zurdo disfrazado de derecha...",
        "id": "1434243133334175_1434358423322646"
    },
    {
        "created_time": "2017-07-21T23:14:38+0000",
        "from": {
            "name": "Hector Raul M.",
            "id": "10152943517803267"
        },
        "message": "Aun es tiempo, aun las elecciones no se han realizado.....TODO PUEDE PASAR......... (y)",
        "id": "1434243133334175_1434344399990715"
    },
    {
        "created_time": "2017-07-22T20:36:07+0000",
        "from": {
            "name": "Victor Hugo",
            "id": "1547381835554025"
        },
        "message": "beatriz chanches quiere regalar regiones al peru y bolivia con mar con la gente con perros gatos minerales asi que se podria considerar una gran candidata presidencial peruana o boliviana ¿crees que miento?? velo y escuchalo tu mismo http://www.cnnchile.com/noticia/2017/04/06/beatriz-sanchez-yo-creo-en-el-aborto-libre   ademas de decir que asesinar bebes en gestacion es libertad",
        "id": "1434243133334175_1435623023196186"
    },
    {
        "created_time": "2017-07-24T14:26:06+0000",
        "from": {
            "name": "Ivan Ahumada Vera",
            "id": "1150421284972995"
        },
        "message": "José Antonio, sea fiel y Dios le honrará.   Firme y adelante.   Paz.",
        "id": "1434243133334175_1438146316277190"
    },
    {
        "created_time": "2017-07-21T21:27:06+0000",
        "from": {
            "name": "Francisco Carbajal Quilcate",
            "id": "10205298271509082"
        },
        "message": "Kast seria un presidente de lujo que tuviera Chile.",
        "id": "1434243133334175_1434254013333087"
    },
    {
        "created_time": "2017-07-21T21:56:11+0000",
        "from": {
            "name": "Luis Jeneral Jeneral",
            "id": "10207327086878313"
        },
        "message": "muy bien, mi voto sera por ud José Antonio Kast saludos",
        "id": "1434243133334175_1434277023330786"
    },
    {
        "created_time": "2017-07-22T15:14:02+0000",
        "from": {
            "name": "Fernanda Maria Viñuela",
            "id": "10208555759645925"
        },
        "message": "Ridiiiiiiiiiiculo legisla como corresponde ignorante!!!!!!!",
        "id": "1434243133334175_1435164913241997"
    },
    {
        "created_time": "2017-07-22T02:24:40+0000",
        "from": {
            "name": "Noemi Peña",
            "id": "10210614454897996"
        },
        "message": "Bien hermanos...somos millones!!!!",
        "id": "1434243133334175_1434477163310772"
    },
    {
        "created_time": "2017-07-23T13:21:43+0000",
        "from": {
            "name": "Родольфо Пьетро Раффаелло Гаглиелми",
            "id": "273540242980536"
        },
        "message": "Muerete facho hijo de puta",
        "id": "1434243133334175_1436760893082399"
    },
    {
        "created_time": "2017-07-22T02:16:49+0000",
        "from": {
            "name": "Nenita Poblete",
            "id": "882552148465111"
        },
        "message": "Vamos José Antonio por la moral.....",
        "id": "1434243133334175_1434468639978291"
    },
    {
        "created_time": "2017-07-21T21:56:59+0000",
        "from": {
            "name": "Angelica Donoso",
            "id": "10202661202398386"
        },
        "message": "Que bueno que los andaba apoyando,lo felicito.",
        "id": "1434243133334175_1434277973330691"
    },
    {
        "created_time": "2017-07-21T22:07:13+0000",
        "from": {
            "name": "Javier Cornejo Albornoz",
            "id": "224585038065691"
        },
        "message": "bendiciones para puerto Montt desde curico",
        "id": "1434243133334175_1434290116662810"
    },
    {
        "created_time": "2017-07-21T22:05:09+0000",
        "from": {
            "name": "Fanny Vergara",
            "id": "1696540217272161"
        },
        "message": "Bieeen !!! Un politico coherente!!",
        "id": "1434243133334175_1434287936663028"
    },
    {
        "created_time": "2017-07-21T21:55:28+0000",
        "from": {
            "name": "Ramon Herrera Fuentealba",
            "id": "10205035664874701"
        },
        "message": "Excelente ..!",
        "id": "1434243133334175_1434276309997524"
    },
    {
        "created_time": "2017-07-21T22:36:30+0000",
        "from": {
            "name": "Carolina Cabello",
            "id": "1174430975923432"
        },
        "message": "por eso y mas sera mi presidente!!!!",
        "id": "1434243133334175_1434313569993798"
    },
    {
        "created_time": "2017-07-22T02:00:08+0000",
        "from": {
            "name": "Bernardita Canto",
            "id": "10205904441430369"
        },
        "message": "Lo queremos en Temuco en la movilización del 5 de agosto! ☺",
        "id": "1434243133334175_1434458603312628"
    },
    {
        "created_time": "2017-07-21T22:26:11+0000",
        "from": {
            "name": "Santiago Arturo Ormeño Cabrera",
            "id": "1473112566129798"
        },
        "message": "X que esto no lo muestra la television vamos arriba que se puede",
        "id": "1434243133334175_1434308013327687"
    },
    {
        "created_time": "2017-07-21T21:26:55+0000",
        "from": {
            "name": "Roberto Vásquez",
            "id": "10206924077364150"
        },
        "message": "Vamos JAK!!! que por Chile hay que luchar",
        "id": "1434243133334175_1434253923333096"
    },
    {
        "created_time": "2017-07-21T21:13:41+0000",
        "from": {
            "name": "Sergio Jara",
            "id": "269189276758834"
        },
        "message": "Por todas partes mi presidente, eso es bueno",
        "id": "1434243133334175_1434244136667408"
    },
    {
        "created_time": "2017-07-21T22:40:50+0000",
        "from": {
            "name": "Ulises Astudillo Corolla",
            "id": "10204875502705278"
        },
        "message": "Firme con Kast 💪💪💪",
        "id": "1434243133334175_1434316453326843"
    },
    {
        "created_time": "2017-07-22T05:36:45+0000",
        "from": {
            "name": "German Gabriel Ortega Rozo",
            "id": "10209542377378730"
        },
        "message": "JAK MI  PRESIDENTE DIOS LE PROTEJA Y BENDIGA",
        "id": "1434243133334175_1434632013295287"
    },
    {
        "created_time": "2017-07-22T04:30:45+0000",
        "from": {
            "name": "Nidia Chavez",
            "id": "10205285030994678"
        },
        "message": "Dios le bendiga!!",
        "id": "1434243133334175_1434570743301414"
    },
    {
        "created_time": "2017-07-22T03:39:28+0000",
        "from": {
            "name": "Laura Vega",
            "id": "193329411039546"
        },
        "message": "Bien!!!",
        "id": "1434243133334175_1434537646638057"
    },
    {
        "created_time": "2017-07-22T00:52:34+0000",
        "from": {
            "name": "Hermogenes Rodrigo Serrano Villegas",
            "id": "1086661594696966"
        },
        "message": "Kast. Lo Máximo.!",
        "id": "1434243133334175_1434404213318067"
    },
    {
        "created_time": "2017-07-21T23:31:15+0000",
        "from": {
            "name": "Emp Libert Mercado",
            "id": "366494870445538"
        },
        "message": "Excelente Jose José Antonio Kast Un candidato de verdad.",
        "id": "1434243133334175_1434353046656517"
    },
    {
        "created_time": "2017-07-22T04:59:47+0000",
        "from": {
            "name": "Alfredo Forján",
            "id": "10207153700788577"
        },
        "message": "Futuro presidente",
        "id": "1434243133334175_1434597483298740"
    },
    {
        "created_time": "2017-07-21T21:13:19+0000",
        "from": {
            "name": "Robinson Salazar",
            "id": "10209030860113831"
        },
        "message": "excelente!!",
        "id": "1434243133334175_1434243923334096"
    },
    {
        "created_time": "2017-07-21T21:14:39+0000",
        "from": {
            "name": "Andres Vigneaux",
            "id": "10207056071826227"
        },
        "message": "Mi voto es para JAK",
        "id": "1434243133334175_1434244663334022"
    },
    {
        "created_time": "2017-07-21T21:23:48+0000",
        "from": {
            "name": "Chile Para Cristo Lavin",
            "id": "821601821252092"
        },
        "message": "BENDICIONES PRESIDENTE",
        "id": "1434243133334175_1434252049999950"
    },
    {
        "created_time": "2017-07-22T04:50:02+0000",
        "from": {
            "name": "Carmen Luisa Muñoz Muñoz",
            "id": "10208273139201074"
        },
        "message": "Muy bien sr. Kast",
        "id": "1434243133334175_1434586679966487"
    },
    {
        "created_time": "2017-07-23T00:27:03+0000",
        "from": {
            "name": "Deborah Fuenzalida Torres",
            "id": "1555295034487511"
        },
        "message": "Bendiciones José Antonio Kast... Dios te ayude en todo",
        "id": "1434243133334175_1435949693163519"
    },
    {
        "created_time": "2017-07-21T21:19:52+0000",
        "from": {
            "name": "Felipe Donoso",
            "id": "159356201295561"
        },
        "message": "vamos presidente !",
        "id": "1434243133334175_1434249296666892"
    },
    {
        "created_time": "2017-07-21T21:17:28+0000",
        "from": {
            "name": "Martín Torres",
            "id": "857686327616883"
        },
        "message": "Y seremos mas",
        "id": "1434243133334175_1434247676667054"
    },
    {
        "created_time": "2017-07-21T21:32:27+0000",
        "from": {
            "name": "David Palma",
            "id": "10212355886553183"
        },
        "message": "Que Dios le bendiga mucho a usted y toda su familia",
        "id": "1434243133334175_1434257023332786"
    },
    {
        "created_time": "2017-07-22T00:24:37+0000",
        "from": {
            "name": "Gloria Pavez",
            "id": "260916280920688"
        },
        "message": "Q lindo lo q mi presidente si o si va ser PRESIDENTE",
        "id": "1434243133334175_1434387929986362"
    },
    {
        "created_time": "2017-07-22T23:56:38+0000",
        "from": {
            "name": "Natalia Isidora",
            "id": "10204189671516815"
        },
        "message": "YO VOTO JAK!",
        "id": "1434243133334175_1435908149834340"
    },
    {
        "created_time": "2017-07-21T21:25:22+0000",
        "from": {
            "name": "Julio Martinez",
            "id": "10155529533210035"
        },
        "message": "Exelente",
        "id": "1434243133334175_1434252809999874"
    },
    {
        "created_time": "2017-07-21T21:13:20+0000",
        "from": {
            "name": "Nestor Ruben Maureira Ortiz",
            "id": "10207870492622895"
        },
        "message": "Bendiciones",
        "id": "1434243133334175_1434243963334092"
    },
    {
        "created_time": "2017-07-21T21:12:46+0000",
        "from": {
            "name": "Alvaro De la Barra",
            "id": "10152743888349448"
        },
        "message": "Bus de la libertad??? o bus de la Familia ????",
        "id": "1434243133334175_1434243700000785"
    },
    {
        "created_time": "2017-07-22T01:00:05+0000",
        "from": {
            "name": "Esperanza Gangas Fuentealb",
            "id": "162046987717008"
        },
        "message": "Bien!",
        "id": "1434243133334175_1434407903317698"
    },
    {
        "created_time": "2017-07-21T21:36:20+0000",
        "from": {
            "name": "Luis Montt",
            "id": "10154881650515112"
        },
        "message": "JAK!!!",
        "id": "1434243133334175_1434259343332554"
    },
    {
        "created_time": "2017-07-21T21:18:51+0000",
        "from": {
            "name": "Karoline Avalos",
            "id": "10203038668396720"
        },
        "message": "",
        "id": "1434243133334175_1434248673333621"
    },
    {
        "created_time": "2017-07-21T21:51:49+0000",
        "from": {
            "name": "Juan Llanca",
            "id": "10210626594397894"
        },
        "message": "Gracias Jose, gracias",
        "id": "1434243133334175_1434273036664518"
    },
    {
        "created_time": "2017-07-22T01:04:27+0000",
        "from": {
            "name": "Maria Isabel Fuenzalida Lizana",
            "id": "864437876902811"
        },
        "message": "https://www.facebook.com/paz.spencer.3/videos/10153595827649430/",
        "id": "1434243133334175_1434413383317150"
    },
    {
        "created_time": "2017-07-22T00:23:33+0000",
        "from": {
            "name": "Sandra Ossandon",
            "id": "2065677296990039"
        },
        "message": "Lindoooooo.",
        "id": "1434243133334175_1434386739986481"
    },
    {
        "created_time": "2017-07-21T21:24:54+0000",
        "from": {
            "name": "Rosalia Astudillo",
            "id": "749116828571752"
        },
        "message": "Que lindo el apoyo!! Acá en Valpo fue horrible.",
        "id": "1434243133334175_1434252579999897"
    },
    {
        "created_time": "2017-07-22T01:14:21+0000",
        "from": {
            "name": "Ilse Pizarro Henríquez",
            "id": "1948454695181666"
        },
        "message": "👏👏👏👏👏👍👍👍👍",
        "id": "1434243133334175_1434419219983233"
    },
    {
        "created_time": "2017-07-21T21:29:48+0000",
        "from": {
            "name": "Tabita Garcia Silva",
            "id": "10206397369998232"
        },
        "message": "",
        "id": "1434243133334175_1434255496666272"
    },
    {
        "created_time": "2017-07-23T14:58:59+0000",
        "from": {
            "name": "Yosef Valenzuela",
            "id": "980561888652863"
        },
        "message": "Y por último hay que leer la historia .",
        "id": "1434243133334175_1436886876403134"
    },
    {
        "created_time": "2017-07-25T03:39:45+0000",
        "from": {
            "name": "Rosa Burgos",
            "id": "465873550286318"
        },
        "message": "Kast",
        "id": "1434243133334175_1438861539539001"
    },
    {
        "created_time": "2017-07-21T21:18:12+0000",
        "from": {
            "name": "Claudia Martínez",
            "id": "259038717904414"
        },
        "message": "La justicia le ha dado la razón al bus de la libertad. https://www.actuall.com/democracia/la-justicia-da-la-razon-al-busdelalibertad-de-hazteoir-org-y-puede-circular-libre-por-madrid/",
        "id": "1434243133334175_1434248263333662"
    },
    {
        "created_time": "2017-07-25T15:49:18+0000",
        "from": {
            "name": "Diego Galarce",
            "id": "10205433126766737"
        },
        "message": "https://www.facebook.com/events/1475627249143734/?ti=cl",
        "id": "1434243133334175_1439538429471312"
    }
]