[
    {
        "created_time": "2017-08-11T22:59:26+0000",
        "from": {
            "name": "Alfredo Cordova Gonzalez",
            "id": "971642012902569"
        },
        "message": "Bien ,Carolina.Los Derechos Humanos no se transan:Son iguales y tienen el mismo valor en Chile,Venezuela o en la India.No se  pueden relativisar por razones   culturales.Valian ayer  ,valen hoy y valdran manana.",
        "id": "641817939361277_641927192683685"
    },
    {
        "created_time": "2017-08-13T05:27:22+0000",
        "from": {
            "name": "Mauricio Brun",
            "id": "10155521190261311"
        },
        "message": "La determinación firme de defender los Derechos Humanos y de elevar los estándares éticos deja una vara demasiado alta para los que abrazan la opción de Piñera. Por eso mi voto es para Carolina Goic.",
        "id": "641817939361277_642465342629870"
    },
    {
        "created_time": "2017-08-12T16:17:03+0000",
        "from": {
            "name": "Marco Mieres Sepulveda",
            "id": "1440938115931379"
        },
        "message": "Además que hablan los demócratas cristianos , si ellos apoyaron a Pinochet de un principio y por último , fueron ellos que colocaron a la unidad popular en el gobierno .",
        "id": "641817939361277_642235909319480"
    },
    {
        "created_time": "2017-08-11T20:58:12+0000",
        "from": {
            "name": "Siervo Miguel Trigo",
            "id": "1652698134965914"
        },
        "message": "Fuerza y Valor Presidenta!  Ud, está cambiando la historia de nuestro amado Chile!",
        "id": "641817939361277_641895199353551"
    },
    {
        "created_time": "2017-08-11T20:36:38+0000",
        "from": {
            "name": "Mónica Tapia Villarroel",
            "id": "10207067260379522"
        },
        "message": "Vamos Carolina Ud será la nueva Presidenta de este país.Saludos desde el fin del mundo",
        "id": "641817939361277_641889286020809"
    },
    {
        "created_time": "2017-08-11T23:09:14+0000",
        "from": {
            "name": "Ester De Lourdes Guerrero Rojas",
            "id": "779505732226251"
        },
        "message": "Ojala que los Democratas Cristianos sigamos exigiendo verdad y justicia para Mario Martinez, un joven estudiante de la Universidad de Santiago, que en epoca de Dictadura fue asesinado por la Dictadura de Pinochet.",
        "id": "641817939361277_641931496016588"
    },
    {
        "created_time": "2017-08-11T23:32:36+0000",
        "from": {
            "name": "Darius Lamour",
            "id": "153351368561047"
        },
        "message": "Felicitaciones Sra. Carolina Goic asi se hace justicia divina.para todos.",
        "id": "641817939361277_641937126016025"
    },
    {
        "created_time": "2017-08-11T22:01:14+0000",
        "from": {
            "name": "Edo Valenzuela",
            "id": "808776519178486"
        },
        "message": "Pero ud apoya una coalición que justifica las violaciones de DDHH en Cuba Venezuela, Bolivia etc  ¿¿¿???",
        "id": "641817939361277_641911172685287"
    },
    {
        "created_time": "2017-08-12T16:14:15+0000",
        "from": {
            "name": "Marco Mieres Sepulveda",
            "id": "1440938115931379"
        },
        "message": "Ella dice estas cosas, pero igual estuvo o está con el gobierno que simpatiza con el gobierno cubano y mejor dicho con el venezolano",
        "id": "641817939361277_642234505986287"
    },
    {
        "created_time": "2017-08-12T16:12:53+0000",
        "from": {
            "name": "Marco Mieres Sepulveda",
            "id": "1440938115931379"
        },
        "message": "Y los dejo para todos los asesinatos de funcionarios de las ffaa en la época de Pinochet",
        "id": "641817939361277_642234122652992"
    },
    {
        "created_time": "2017-08-12T03:33:43+0000",
        "from": {
            "name": "Ingrid De Baeremaecker",
            "id": "10152510050407766"
        },
        "message": "Pero qué justicia quieren?! Si los q lo hicieron ya están muertos o desahuciados",
        "id": "641817939361277_642006859342385"
    },
    {
        "created_time": "2017-08-12T04:26:11+0000",
        "from": {
            "name": "Vicky N. Saleh",
            "id": "10203436566731699"
        },
        "message": "Y los derechos de los niños de Chile???  Como es posible que se permita que Las deudas de pensión alimenticia de los infelices que abandonaron a sus hijos prescriban!?!??!?! ! Donde esta el castigo para esos irresponsables??",
        "id": "641817939361277_642025202673884"
    },
    {
        "created_time": "2017-08-11T18:28:50+0000",
        "from": {
            "name": "Carlos Duran Hidalgo",
            "id": "10214474976210478"
        },
        "message": "Bieeen presidenta",
        "id": "641817939361277_641849526024785"
    },
    {
        "created_time": "2017-08-11T18:51:32+0000",
        "from": {
            "name": "Mónica Tapia Villarroel",
            "id": "10207067260379522"
        },
        "message": "que alegría!!!!",
        "id": "641817939361277_641854386024299"
    },
    {
        "created_time": "2017-08-11T18:18:49+0000",
        "from": {
            "name": "Silvia Espinoza",
            "id": "316863065446056"
        },
        "message": "Bien Sra.Carolina Goic",
        "id": "641817939361277_641847409358330"
    },
    {
        "created_time": "2017-08-11T23:25:35+0000",
        "from": {
            "name": "Manuel Villagran",
            "id": "543787509122431"
        },
        "message": "Es volver a creer en la política de antes.",
        "id": "641817939361277_641935062682898"
    },
    {
        "created_time": "2017-08-11T18:46:03+0000",
        "from": {
            "name": "Estela Gonzalez",
            "id": "1942831482646270"
        },
        "message": "",
        "id": "641817939361277_641853429357728"
    },
    {
        "created_time": "2017-08-12T16:17:45+0000",
        "from": {
            "name": "Marco Mieres Sepulveda",
            "id": "1440938115931379"
        },
        "message": "Y que considencia que estas cosas pasen en fecha de elecciones",
        "id": "641817939361277_642236119319459"
    },
    {
        "created_time": "2017-08-12T16:15:51+0000",
        "from": {
            "name": "Marco Mieres Sepulveda",
            "id": "1440938115931379"
        },
        "message": "Los derechos humanos son para ambos lados",
        "id": "641817939361277_642235215986216"
    },
    {
        "created_time": "2017-08-11T20:00:14+0000",
        "from": {
            "name": "Ricardo Leiva Lanz",
            "id": "10205535618617503"
        },
        "message": "Tenía buena opinión de la Goic!",
        "id": "641817939361277_641871072689297"
    },
    {
        "created_time": "2017-08-12T09:31:45+0000",
        "from": {
            "name": "David Bravo Cisternas",
            "id": "10202829977416565"
        },
        "message": "Y los niños del sename no tienen derechos",
        "id": "641817939361277_642114079331663"
    },
    {
        "created_time": "2017-08-13T04:39:14+0000",
        "from": {
            "name": "Nicolas Radovic Plata",
            "id": "10204610399115467"
        },
        "message": "Patetica",
        "id": "641817939361277_642451615964576"
    },
    {
        "created_time": "2017-08-11T23:55:08+0000",
        "from": {
            "name": "Alejandro Julian Espinoza",
            "id": "872305979577384"
        },
        "message": "Gran Líder Carolina. y veronica defendiendo a maduro",
        "id": "641817939361277_641942062682198"
    }
]